smartestate/__init__.py
smartestate/asgi.py
smartestate/context_processors.py
smartestate/functions.py
smartestate/settings.py
smartestate/urls.py
smartestate/views.py
smartestate/wsgi.py
smartestate/locale/de/LC_MESSAGES/django.mo
smartestate/locale/de/LC_MESSAGES/django.po
smartestate/locale/es/LC_MESSAGES/django.mo
smartestate/locale/es/LC_MESSAGES/django.po
smartestate/locale/fr/LC_MESSAGES/django.mo
smartestate/locale/fr/LC_MESSAGES/django.po
smartestate/locale/it/LC_MESSAGES/django.mo
smartestate/locale/it/LC_MESSAGES/django.po
smartestate/templates/smartestate/base.html
smartestate/templates/smartestate/home.html
smartestate-0.3.3.dist-info/licenses/LICENSE
smartestate-0.3.3.dist-info/METADATA
smartestate-0.3.3.dist-info/WHEEL
smartestate-0.3.3.dist-info/top_level.txt
smartestate-0.3.3.dist-info/RECORD
