Metadata-Version: 2.4
Name: smartestate
Version: 0.3.3
Summary: Django site for real estate brokers
Author-email: Belal Ibrahim <belal.ibrahim@proton.me>
License:                                  Apache License
Project-URL: Homepage, https://github.com/belal-i/smartestate
Project-URL: Repository, https://github.com/belal-i/smartestate
Classifier: Development Status :: 4 - Beta
Classifier: Environment :: Web Environment
Classifier: Framework :: Django
Classifier: Programming Language :: Python :: 3
Classifier: Intended Audience :: Financial and Insurance Industry
Classifier: Intended Audience :: Developers
Classifier: Intended Audience :: Information Technology
Classifier: Intended Audience :: System Administrators
Classifier: License :: OSI Approved :: Apache Software License
Requires-Python: >=3.8
License-File: LICENSE
Requires-Dist: Django>=4.2.24,>=5.1.12,>=5.2.6
Requires-Dist: datetime
Requires-Dist: Pillow
Requires-Dist: django-cookie-consent>=0.3.2
Requires-Dist: djangorestframework
Requires-Dist: django-widget-tweaks
Requires-Dist: django-modeltranslation
Requires-Dist: environs
Requires-Dist: mysqlclient
Requires-Dist: whitenoise
Dynamic: license-file
